<?xml version="1.0" encoding="UTF-8"?><record_update table="par_dashboard_visibility">
    <par_dashboard_visibility action="INSERT_OR_UPDATE">
        <dashboard display_value="test">1bc2d00997e51110870cf3ffe153af6b</dashboard>
        <experience display_value="portalMock">6e97f3064dc91510e0a45d9de01e5de9</experience>
        <sys_class_name>par_dashboard_visibility</sys_class_name>
        <sys_created_by>admin</sys_created_by>
        <sys_created_on>2022-08-24 09:24:29</sys_created_on>
        <sys_id>d7c2580997e51110870cf3ffe153af6a</sys_id>
        <sys_name/>
        <sys_package display_value="portalMock" source="x_866082_portalpro">de676b8e2f491510cc4e57892799b6b7</sys_package>
        <sys_policy/>
        <sys_scope display_value="portalMock">de676b8e2f491510cc4e57892799b6b7</sys_scope>
        <sys_update_name>par_dashboard_visibility_d7c2580997e51110870cf3ffe153af6a</sys_update_name>
    </par_dashboard_visibility>
</record_update>
